p_2/Batch.py
p_2/__init__.py
p_2-1.0.1.dist-info/LICENSE
p_2-1.0.1.dist-info/METADATA
p_2-1.0.1.dist-info/WHEEL
p_2-1.0.1.dist-info/entry_points.txt
p_2-1.0.1.dist-info/top_level.txt
p_2-1.0.1.dist-info/RECORD
