Metadata-Version: 2.1
Name: p-2
Version: 1.0.1
Summary: A Python package to get my name
Home-page: https://github.com/agmukul
Author: Abhishek
Author-email: abhishek08arora@gmail.com
License: MIT
Platform: UNKNOWN
Classifier: License :: OSI Approved :: MIT License
Classifier: Programming Language :: Python :: 3
Classifier: Programming Language :: Python :: 3.7
